torswitch/__init__.py
torswitch/status.py
torswitch/tor.py
torswitch-21.9.16.dist-info/LICENSE
torswitch-21.9.16.dist-info/METADATA
torswitch-21.9.16.dist-info/WHEEL
torswitch-21.9.16.dist-info/top_level.txt
torswitch-21.9.16.dist-info/RECORD
