Metadata-Version: 2.1
Name: torswitch
Version: 21.9.16
Summary: A basic package for using tor proxy with python.
Home-page: UNKNOWN
Author: Alex Deathway
Author-email: <alexdeathway@gmail.com>
License: UNKNOWN
Keywords: python,tor,pythontor,iprotation,ipaddress
Platform: UNKNOWN
Classifier: Development Status :: 1 - Planning
Classifier: Intended Audience :: Developers
Classifier: Programming Language :: Python :: 3
Classifier: Operating System :: Unix
Classifier: Operating System :: MacOS :: MacOS X
Requires-Dist: PySocks (==1.7.1)
Requires-Dist: certifi (==2021.5.30)
Requires-Dist: charset-normalizer (==2.0.4)
Requires-Dist: idna (==3.2)
Requires-Dist: requests (==2.26.0)
Requires-Dist: stem (==1.8.0)
Requires-Dist: urllib3 (==1.26.6)
